tom_lt/__init__.py
tom_lt/lt.py
tom_lt-0.4.3.dist-info/LICENSE
tom_lt-0.4.3.dist-info/METADATA
tom_lt-0.4.3.dist-info/WHEEL
tom_lt-0.4.3.dist-info/RECORD
