Metadata-Version: 2.1
Name: tom-lt
Version: 0.4.3
Summary: TOM Toolkit Facility module for the Liverpool Telescope
License: GPL-3.0-or-later
Author: Doug Arnold
Author-email: d.m.arnold@ljmu.ac.uk
Requires-Python: >=3.8.1,<3.12
Classifier: License :: OSI Approved :: GNU General Public License v3 or later (GPLv3+)
Classifier: Programming Language :: Python :: 3
Classifier: Programming Language :: Python :: 3.9
Classifier: Programming Language :: Python :: 3.10
Classifier: Programming Language :: Python :: 3.11
Requires-Dist: lxml (>=5.2,<5.4)
Requires-Dist: suds-py3 (>=1.4,<1.5)
Requires-Dist: tomtoolkit (>=2.15)
